{
  "id": "guido-van-rossum",
  "name": "Guido van Rossum",
  "email": "",
  "gender": "male",
  "nationality": "Dutch",
  "profile_page": "",
  "thumbnail": "",
  "websites": [{
    "id": 1,
    "name": "Guido's persoonlijke pagina",
    "url": "https://gvanrossum.github.io/"
  },{
    "id": 2,
    "name": "Python",
    "url": "https://www.python.org"
  }],
  "social": {
    "facebook": "",
    "github": "",
    "instagram": "",
    "linkedin": "https://www.linkedin.com/in/guido-van-rossum-4a0756/",
    "mastodon": "",
    "mastodon_url": "",
    "twitter": "gvanrossum"
  }
}
